Pyinger/__init__.py
Pyinger/checker.py
Pyinger-0.0.6.dist-info/METADATA
Pyinger-0.0.6.dist-info/WHEEL
Pyinger-0.0.6.dist-info/top_level.txt
Pyinger-0.0.6.dist-info/RECORD
