Metadata-Version: 2.1
Name: Pyinger
Version: 0.0.6
Summary: Ping library that will check if server is up or down
Home-page: https://github.com/seanp97/PyServerChecker
Author: Sean Pelser
Author-email: <sean.pelser97@gmail.com>
License: UNKNOWN
Keywords: python,ping,pinger,server,server checker,pyinger
Platform: UNKNOWN
Classifier: Development Status :: 3 - Alpha
Classifier: Intended Audience :: Developers
Classifier: Programming Language :: Python :: 3
Classifier: Operating System :: Unix
Classifier: Operating System :: MacOS :: MacOS X
Classifier: Operating System :: Microsoft :: Windows
Requires-Dist: colorama
Requires-Dist: ping3
